{
	"ulid": "01J2H936WZAG7A1GSAEY1Y2S14",
	"minTime": 1720451577075,
	"maxTime": 1720634400000,
	"stats": {
		"numSamples": 6692462,
		"numSeries": 25346,
		"numChunks": 76086
	},
	"compaction": {
		"level": 4,
		"sources": [
			"01J29RS39YDQA0NFHMCQSW45ZA",
			"01J29VF932A5D5ZKFASAC0WMXP",
			"01J2BPA0PZP1B7BXB1CYEZ50DN",
			"01J2BPA0ZPSV96JQ71HMDVA3QC",
			"01J2C0KG2DYQS6R28K69JJDEJR",
			"01J2EB38XRVYAD2B6JFB0Z88M9",
			"01J2EB393AFG09NB760J8YX6R5",
			"01J2EP5G3JD4GJ8165M9944BHF",
			"01J2EW9C1DJB38TMM7VYQC2ZBB",
			"01J2F08NZQMMFE5YHSZYPHF5J0"
		],
		"parents": [
			{
				"ulid": "01J2EB39WKKE3A8VB9GYK4ZQQD",
				"minTime": 1720451577075,
				"maxTime": 1720476000000
			},
			{
				"ulid": "01J2EW9CD0VVBJNT6YPFQ4J1KM",
				"minTime": 1720526891632,
				"maxTime": 1720548000000
			},
			{
				"ulid": "01J2H936MKH1N5KDR48Z9R6E1J",
				"minTime": 1720615805306,
				"maxTime": 1720634400000
			}
		]
	},
	"version": 1
}